CodOpY/__init__.py
CodOpY/clone.py
CodOpY/misc.py
CodOpY/optimise.py
CodOpY/plot.py
CodOpY/Data/HEK.csv
CodOpY/Data/RE_List.csv
CodOpY/Data/Scer.csv
CodOpY-0.2.0.dist-info/LICENSE.txt
CodOpY-0.2.0.dist-info/METADATA
CodOpY-0.2.0.dist-info/WHEEL
CodOpY-0.2.0.dist-info/top_level.txt
CodOpY-0.2.0.dist-info/RECORD
